{"51165": {"past_margin": "R +41", "unemployment": 4.1, "census": {"percent_bachelors": 0.237273544659767, "median_income": 53728.0, "percent_white": 0.9065615101170083, "population": 77345.0, "percent_hispanic": 0.05691382765531062, "percent_black": 0.015812269700691706}}, "51057": {"past_margin": "D +7", "unemployment": 5.4, "census": {"percent_bachelors": 0.13681076883251359, "median_income": 42143.0, "percent_white": 0.5546301271717714, "population": 11166.0, "percent_hispanic": 0.033942324914920295, "percent_black": 0.3734551316496507}}, "51107": {"past_margin": "D +4", "unemployment": 3.6, "census": {"percent_bachelors": 0.5799543065178223, "median_income": 123966.0, "percent_white": 0.603518275914976, "population": 338916.0, "percent_hispanic": 0.12990829586092129, "percent_black": 0.07341052060097487}}, "51075": {"past_margin": "R +28", "unemployment": 4.1, "census": {"percent_bachelors": 0.38310643564356434, "median_income": 82460.0, "percent_white": 0.7716742960188653, "population": 21627.0, "percent_hispanic": 0.022055763628797336, "percent_black": 0.19679104822675358}}, "51177": {"past_margin": "R +12", "unemployment": 4.6, "census": {"percent_bachelors": 0.28307733764483967, "median_income": 78505.0, "percent_white": 0.7113708399366085, "population": 126200.0, "percent_hispanic": 0.08110935023771791, "percent_black": 0.15852614896988906}}, "51610": {"past_margin": "D +40", "unemployment": 3.0, "census": {"percent_bachelors": 0.7509149130832571, "median_income": 120500.0, "percent_white": 0.7272449135689154, "population": 13074.0, "percent_hispanic": 0.09476824231298761, "percent_black": 0.055377084289429404}}, "51063": {"past_margin": "R +25", "unemployment": 4.0, "census": {"percent_bachelors": 0.16699236098774206, "median_income": 47543.0, "percent_white": 0.9396194667356976, "population": 15452.0, "percent_hispanic": 0.026727931659332127, "percent_black": 0.020903442920010354}}, "51041": {"past_margin": "R +7", "unemployment": 4.3, "census": {"percent_bachelors": 0.36609095037665795, "median_income": 72514.0, "percent_white": 0.6420544063736175, "population": 324337.0, "percent_hispanic": 0.0759364488171254, "percent_black": 0.226582227744599}}, "51570": {"past_margin": "R +40", "unemployment": 4.7, "census": {"percent_bachelors": 0.19554558298013797, "median_income": 52529.0, "percent_white": 0.780811766047201, "population": 17542.0, "percent_hispanic": 0.046744954965226314, "percent_black": 0.1380686352753392}}, "51087": {"past_margin": "D +12", "unemployment": 4.3, "census": {"percent_bachelors": 0.3967225823323931, "median_income": 61438.0, "percent_white": 0.5593055088002338, "population": 314878.0, "percent_hispanic": 0.051775608330845595, "percent_black": 0.2957780473707277}}, "51033": {"past_margin": "D +8", "unemployment": 5.1, "census": {"percent_bachelors": 0.1927157001414427, "median_income": 58417.0, "percent_white": 0.637643252916681, "population": 29057.0, "percent_hispanic": 0.03771896616994184, "percent_black": 0.2912551192483739}}, "51036": {"past_margin": "D +33", "unemployment": 5.2, "census": {"percent_bachelors": 0.11765788989136439, "median_income": 48088.0, "percent_white": 0.4084428291864691, "population": 7154.0, "percent_hispanic": 0.015655577299412915, "percent_black": 0.4851831143416271}}, "51678": {"past_margin": "D +13", "unemployment": 7.5, "census": {"percent_bachelors": 0.447886144830473, "median_income": 36840.0, "percent_white": 0.8221816137194264, "population": 7114.0, "percent_hispanic": 0.04188923249929716, "percent_black": 0.0639583919032893}}, "51145": {"past_margin": "R +46", "unemployment": 3.9, "census": {"percent_bachelors": 0.28039800995024877, "median_income": 75447.0, "percent_white": 0.8294966835739368, "population": 28193.0, "percent_hispanic": 0.019153690632426487, "percent_black": 0.12712375412336396}}, "51079": {"past_margin": "R +25", "unemployment": 3.7, "census": {"percent_bachelors": 0.2448361546824041, "median_income": 63739.0, "percent_white": 0.8523926249600341, "population": 18766.0, "percent_hispanic": 0.04598742406479804, "percent_black": 0.06740914419695193}}, "51119": {"past_margin": "R +21", "unemployment": 4.3, "census": {"percent_bachelors": 0.2833613849483049, "median_income": 54452.0, "percent_white": 0.7821946935379496, "population": 10817.0, "percent_hispanic": 0.018674308958121475, "percent_black": 0.19376906720902284}}, "51185": {"past_margin": "R +57", "unemployment": 7.5, "census": {"percent_bachelors": 0.1280886912404873, "median_income": 36248.0, "percent_white": 0.9422074846044529, "population": 44331.0, "percent_hispanic": 0.007985382689314474, "percent_black": 0.02754280300466942}}, "51023": {"past_margin": "R +39", "unemployment": 4.2, "census": {"percent_bachelors": 0.25392560248551516, "median_income": 63011.0, "percent_white": 0.9351759552937623, "population": 33105.0, "percent_hispanic": 0.01295876755777073, "percent_black": 0.03751699139102854}}, "51830": {"past_margin": "D +29", "unemployment": 6.3, "census": {"percent_bachelors": 0.4863916947250281, "median_income": 48057.0, "percent_white": 0.6963405319075064, "population": 14401.0, "percent_hispanic": 0.06957850149295187, "percent_black": 0.14804527463370598}}, "51021": {"past_margin": "R +48", "unemployment": 5.8, "census": {"percent_bachelors": 0.1418892760356175, "median_income": 43508.0, "percent_white": 0.9487141370596105, "population": 6727.0, "percent_hispanic": 0.004013676230117437, "percent_black": 0.04489371190723948}}, "51640": {"past_margin": "R +19", "unemployment": 5.5, "census": {"percent_bachelors": 0.12389911929543634, "median_income": 30430.0, "percent_white": 0.7556224036670964, "population": 6981.0, "percent_hispanic": 0.1847872797593468, "percent_black": 0.04512247529007306}}, "51045": {"past_margin": "R +35", "unemployment": 5.5, "census": {"percent_bachelors": 0.1310999736217357, "median_income": 46658.0, "percent_white": 0.9675374567806377, "population": 5206.0, "percent_hispanic": 0.0, "percent_black": 0.001920860545524395}}, "51770": {"past_margin": "D +22", "unemployment": 4.9, "census": {"percent_bachelors": 0.24087956021989004, "median_income": 39530.0, "percent_white": 0.6129312193080072, "population": 97949.0, "percent_hispanic": 0.057162400841254124, "percent_black": 0.2786041715586683}}, "51121": {"past_margin": "R +0", "unemployment": 4.3, "census": {"percent_bachelors": 0.4428840222683452, "median_income": 44810.0, "percent_white": 0.8500960253841016, "population": 95808.0, "percent_hispanic": 0.028828490313961255, "percent_black": 0.04217810621242485}}, "51025": {"past_margin": "D +25", "unemployment": 6.8, "census": {"percent_bachelors": 0.13316811235026849, "median_income": 37028.0, "percent_white": 0.40563646011438004, "population": 16961.0, "percent_hispanic": 0.018630976947113968, "percent_black": 0.5638818465892341}}, "51775": {"past_margin": "R +21", "unemployment": 4.4, "census": {"percent_bachelors": 0.30666110581506195, "median_income": 50590.0, "percent_white": 0.8631767515923567, "population": 25120.0, "percent_hispanic": 0.028463375796178345, "percent_black": 0.07921974522292993}}, "51073": {"past_margin": "R +28", "unemployment": 4.1, "census": {"percent_bachelors": 0.22884144475053567, "median_income": 60980.0, "percent_white": 0.8536737235367372, "population": 36938.0, "percent_hispanic": 0.028398938762250258, "percent_black": 0.08806648979370837}}, "51195": {"past_margin": "R +49", "unemployment": 8.3, "census": {"percent_bachelors": 0.12839270568278202, "median_income": 37357.0, "percent_white": 0.9209972597377177, "population": 40872.0, "percent_hispanic": 0.012086513994910942, "percent_black": 0.052431982775494226}}, "51760": {"past_margin": "D +56", "unemployment": 5.2, "census": {"percent_bachelors": 0.3538416249632028, "median_income": 41331.0, "percent_white": 0.3965451073849988, "population": 211063.0, "percent_hispanic": 0.06399984838650072, "percent_black": 0.4889251076692741}}, "51059": {"past_margin": "D +20", "unemployment": 3.6, "census": {"percent_bachelors": 0.5924330946719448, "median_income": 112102.0, "percent_white": 0.5318627626509302, "population": 1117072.0, "percent_hispanic": 0.16017051720927566, "percent_black": 0.09317483564174914}}, "51197": {"past_margin": "R +37", "unemployment": 5.4, "census": {"percent_bachelors": 0.15192690086166083, "median_income": 40185.0, "percent_white": 0.9424792371577976, "population": 29259.0, "percent_hispanic": 0.010560853070849995, "percent_black": 0.03718513961516115}}, "51730": {"past_margin": "D +80", "unemployment": 9.0, "census": {"percent_bachelors": 0.148625936861231, "median_income": 33927.0, "percent_white": 0.15549184623447085, "population": 32439.0, "percent_hispanic": 0.04109251209963316, "percent_black": 0.7737291531798144}}, "51155": {"past_margin": "R +25", "unemployment": 5.0, "census": {"percent_bachelors": 0.16411378555798686, "median_income": 45635.0, "percent_white": 0.9126191163730869, "population": 34630.0, "percent_hispanic": 0.013629800750794108, "percent_black": 0.06009240542881894}}, "51530": {"past_margin": "R +26", "unemployment": 5.2, "census": {"percent_bachelors": 0.13950143815915628, "median_income": 32789.0, "percent_white": 0.890767619332635, "population": 6683.0, "percent_hispanic": 0.007780936705072572, "percent_black": 0.03187191381116265}}, "51169": {"past_margin": "R +51", "unemployment": 5.1, "census": {"percent_bachelors": 0.11590569979110714, "median_income": 36579.0, "percent_white": 0.9708090075062552, "population": 22781.0, "percent_hispanic": 0.01202756683200913, "percent_black": 0.007067292919538211}}, "51153": {"past_margin": "D +16", "unemployment": 4.1, "census": {"percent_bachelors": 0.3813473734238315, "median_income": 98514.0, "percent_white": 0.4696482046402284, "population": 428772.0, "percent_hispanic": 0.2116416183892605, "percent_black": 0.20103225024022092}}, "51683": {"past_margin": "D +13", "unemployment": 4.1, "census": {"percent_bachelors": 0.2914140813819882, "median_income": 71215.0, "percent_white": 0.45548521119794244, "population": 40436.0, "percent_hispanic": 0.32468592343456326, "percent_black": 0.14501928974181422}}, "51161": {"past_margin": "R +26", "unemployment": 3.9, "census": {"percent_bachelors": 0.3398359298562505, "median_income": 60950.0, "percent_white": 0.8754640856707513, "population": 93194.0, "percent_hispanic": 0.02454020645105908, "percent_black": 0.05548640470416551}}, "51143": {"past_margin": "R +28", "unemployment": 5.3, "census": {"percent_bachelors": 0.1400518955053215, "median_income": 42311.0, "percent_white": 0.7427051068223334, "population": 62955.0, "percent_hispanic": 0.023143515209276468, "percent_black": 0.21399412278611707}}, "51003": {"past_margin": "D +12", "unemployment": 3.9, "census": {"percent_bachelors": 0.5208747222344856, "median_income": 67958.0, "percent_white": 0.7748986582648725, "population": 101883.0, "percent_hispanic": 0.05592689653818596, "percent_black": 0.09438277239578732}}, "51157": {"past_margin": "R +8", "unemployment": 4.1, "census": {"percent_bachelors": 0.3200071710290427, "median_income": 59753.0, "percent_white": 0.8920225624496374, "population": 7446.0, "percent_hispanic": 0.03263497179693795, "percent_black": 0.0381412839108246}}, "51790": {"past_margin": "D +4", "unemployment": 4.4, "census": {"percent_bachelors": 0.3145941481831052, "median_income": 39982.0, "percent_white": 0.820321564727333, "population": 24132.0, "percent_hispanic": 0.024987568373943312, "percent_black": 0.11648433615116857}}, "51109": {"past_margin": "R +14", "unemployment": 4.3, "census": {"percent_bachelors": 0.19164080281398718, "median_income": 57126.0, "percent_white": 0.7696707465252052, "population": 33743.0, "percent_hispanic": 0.024419879678748185, "percent_black": 0.1671161426073556}}, "51183": {"past_margin": "D +25", "unemployment": 6.8, "census": {"percent_bachelors": 0.08976500723911349, "median_income": 36972.0, "percent_white": 0.3858928122116917, "population": 11923.0, "percent_hispanic": 0.032961502977438564, "percent_black": 0.5703262601694205}}, "51163": {"past_margin": "R +18", "unemployment": 5.0, "census": {"percent_bachelors": 0.23500751879699247, "median_income": 48550.0, "percent_white": 0.9335628381097152, "population": 22367.0, "percent_hispanic": 0.014575043591004606, "percent_black": 0.028658291232619485}}, "51105": {"past_margin": "R +44", "unemployment": 7.2, "census": {"percent_bachelors": 0.11130856219709208, "median_income": 31264.0, "percent_white": 0.9315208825847123, "population": 25380.0, "percent_hispanic": 0.01706067769897557, "percent_black": 0.03475177304964539}}, "51580": {"past_margin": "D +15", "unemployment": 6.1, "census": {"percent_bachelors": 0.08992985971943888, "median_income": 38176.0, "percent_white": 0.8207756705962754, "population": 5853.0, "percent_hispanic": 0.012472236459935076, "percent_black": 0.13736545361353153}}, "51127": {"past_margin": "R +34", "unemployment": 3.8, "census": {"percent_bachelors": 0.24640762463343108, "median_income": 73030.0, "percent_white": 0.7983009329233335, "population": 19187.0, "percent_hispanic": 0.02345337989263564, "percent_black": 0.12993172460520144}}, "51089": {"past_margin": "R +15", "unemployment": 6.5, "census": {"percent_bachelors": 0.1151559403358715, "median_income": 34344.0, "percent_white": 0.7092522658610272, "population": 52960.0, "percent_hispanic": 0.05026435045317221, "percent_black": 0.21873111782477342}}, "51013": {"past_margin": "D +40", "unemployment": 2.8, "census": {"percent_bachelors": 0.719748224037114, "median_income": 105120.0, "percent_white": 0.6324799135225482, "population": 220173.0, "percent_hispanic": 0.15448760747230586, "percent_black": 0.08336172010191985}}, "51137": {"past_margin": "R +15", "unemployment": 4.6, "census": {"percent_bachelors": 0.2395291768914029, "median_income": 63538.0, "percent_white": 0.79832939046117, "population": 34239.0, "percent_hispanic": 0.038494114898215484, "percent_black": 0.12769064517071177}}, "51097": {"past_margin": "R +3", "unemployment": 4.8, "census": {"percent_bachelors": 0.16773343373493976, "median_income": 47804.0, "percent_white": 0.6579951929874169, "population": 7073.0, "percent_hispanic": 0.03166972995899901, "percent_black": 0.280927470663085}}, "51117": {"past_margin": "R +7", "unemployment": 6.2, "census": {"percent_bachelors": 0.15168755614492876, "median_income": 37756.0, "percent_white": 0.594553943533983, "population": 31913.0, "percent_hispanic": 0.025318835584244664, "percent_black": 0.35534108357095856}}, "51011": {"past_margin": "R +36", "unemployment": 4.9, "census": {"percent_bachelors": 0.15284327323162275, "median_income": 47927.0, "percent_white": 0.7669287177115677, "population": 15137.0, "percent_hispanic": 0.01169320208759992, "percent_black": 0.19970932153002577}}, "51083": {"past_margin": "R +6", "unemployment": 6.4, "census": {"percent_bachelors": 0.14637601322105925, "median_income": 35093.0, "percent_white": 0.6009410710284562, "population": 35704.0, "percent_hispanic": 0.017841138247815372, "percent_black": 0.3701546045261035}}, "51820": {"past_margin": "R +11", "unemployment": 4.7, "census": {"percent_bachelors": 0.1902836829999303, "median_income": 45499.0, "percent_white": 0.7860414600746093, "population": 21177.0, "percent_hispanic": 0.06577891108277849, "percent_black": 0.12244416111819427}}, "51061": {"past_margin": "R +20", "unemployment": 3.9, "census": {"percent_bachelors": 0.34257626520895784, "median_income": 92078.0, "percent_white": 0.814090459491053, "population": 66726.0, "percent_hispanic": 0.06746995174294877, "percent_black": 0.07538290921080239}}, "51065": {"past_margin": "R +6", "unemployment": 3.7, "census": {"percent_bachelors": 0.2963443651308674, "median_income": 64641.0, "percent_white": 0.7882443630757371, "population": 25945.0, "percent_hispanic": 0.03133551744074003, "percent_black": 0.1401811524378493}}, "51720": {"past_margin": "R +22", "unemployment": 7.0, "census": {"percent_bachelors": 0.20465640255351109, "median_income": 36148.0, "percent_white": 0.9023661270236613, "population": 4015.0, "percent_hispanic": 0.019925280199252802, "percent_black": 0.06973848069738481}}, "51009": {"past_margin": "R +20", "unemployment": 4.8, "census": {"percent_bachelors": 0.183277442432372, "median_income": 44765.0, "percent_white": 0.7570493532276577, "population": 32237.0, "percent_hispanic": 0.02062847039116543, "percent_black": 0.18615255762012595}}, "51181": {"past_margin": "D +21", "unemployment": 5.2, "census": {"percent_bachelors": 0.18774101887558353, "median_income": 51527.0, "percent_white": 0.5161946259985476, "population": 6885.0, "percent_hispanic": 0.0063907044299201165, "percent_black": 0.46390704429920115}}, "51540": {"past_margin": "D +53", "unemployment": 3.7, "census": {"percent_bachelors": 0.49338559529642334, "median_income": 47218.0, "percent_white": 0.6639703404111897, "population": 44505.0, "percent_hispanic": 0.04927536231884058, "percent_black": 0.1964498370969554}}, "51015": {"past_margin": "R +42", "unemployment": 4.1, "census": {"percent_bachelors": 0.21205785964515764, "median_income": 54018.0, "percent_white": 0.919519177283026, "population": 73707.0, "percent_hispanic": 0.02261657644457107, "percent_black": 0.04109514700096328}}, "51173": {"past_margin": "R +33", "unemployment": 6.5, "census": {"percent_bachelors": 0.1486959565902328, "median_income": 37880.0, "percent_white": 0.9469820554649266, "population": 31876.0, "percent_hispanic": 0.0177876772493412, "percent_black": 0.020799347471451877}}, "51810": {"past_margin": "R +3", "unemployment": 4.3, "census": {"percent_bachelors": 0.33497821158519203, "median_income": 67001.0, "percent_white": 0.6358827977909578, "population": 445623.0, "percent_hispanic": 0.07216413874508272, "percent_black": 0.19177421273138953}}, "51091": {"past_margin": "R +33", "unemployment": 3.5, "census": {"percent_bachelors": 0.19435215946843853, "median_income": 44132.0, "percent_white": 0.9982285208148804, "population": 2258.0, "percent_hispanic": 0.0, "percent_black": 0.0}}, "51081": {"past_margin": "D +28", "unemployment": 5.4, "census": {"percent_bachelors": 0.08494952931836225, "median_income": 38933.0, "percent_white": 0.37595499958021994, "population": 11911.0, "percent_hispanic": 0.02031735370665771, "percent_black": 0.5969272101418857}}, "51085": {"past_margin": "R +37", "unemployment": 3.9, "census": {"percent_bachelors": 0.3634998896166017, "median_income": 77550.0, "percent_white": 0.8476099673251298, "population": 100689.0, "percent_hispanic": 0.023815908391184738, "percent_black": 0.09263176712451211}}, "51047": {"past_margin": "R +16", "unemployment": 4.3, "census": {"percent_bachelors": 0.21395845101361954, "median_income": 65235.0, "percent_white": 0.7166562304320601, "population": 47910.0, "percent_hispanic": 0.08881235650177416, "percent_black": 0.14237111250260906}}, "51660": {"past_margin": "D +13", "unemployment": 5.3, "census": {"percent_bachelors": 0.35649017933390265, "median_income": 38807.0, "percent_white": 0.6977627358769013, "population": 50821.0, "percent_hispanic": 0.17295999685169516, "percent_black": 0.0729619645422168}}, "51750": {"past_margin": "D +4", "unemployment": 5.6, "census": {"percent_bachelors": 0.3491471979360757, "median_income": 30284.0, "percent_white": 0.8402283293120697, "population": 16993.0, "percent_hispanic": 0.02789383863943977, "percent_black": 0.0879774024598364}}, "51620": {"past_margin": "D +31", "unemployment": 6.7, "census": {"percent_bachelors": 0.1983942908117752, "median_income": 33133.0, "percent_white": 0.3820014061401453, "population": 8534.0, "percent_hispanic": 0.0058589172720881185, "percent_black": 0.5796812749003984}}, "51595": {"past_margin": "D +34", "unemployment": 7.0, "census": {"percent_bachelors": 0.14962269060629715, "median_income": 30240.0, "percent_white": 0.3101020767335445, "population": 5682.0, "percent_hispanic": 0.010383667722632876, "percent_black": 0.6538190777895108}}, "51005": {"past_margin": "R +3", "unemployment": 5.1, "census": {"percent_bachelors": 0.1691449814126394, "median_income": 45183.0, "percent_white": 0.921217380524391, "population": 16133.0, "percent_hispanic": 0.013326721626479887, "percent_black": 0.05039360317361929}}, "51670": {"past_margin": "D +16", "unemployment": 7.5, "census": {"percent_bachelors": 0.10890955654400862, "median_income": 39156.0, "percent_white": 0.5179441340782123, "population": 22375.0, "percent_hispanic": 0.06739664804469274, "percent_black": 0.3761340782122905}}, "51125": {"past_margin": "D +3", "unemployment": 4.0, "census": {"percent_bachelors": 0.2895121505572812, "median_income": 50131.0, "percent_white": 0.8182917002417406, "population": 14892.0, "percent_hispanic": 0.03323932312651088, "percent_black": 0.13644910018802042}}, "51067": {"past_margin": "R +29", "unemployment": 4.6, "census": {"percent_bachelors": 0.19796840850387443, "median_income": 44827.0, "percent_white": 0.8708126330731015, "population": 56360.0, "percent_hispanic": 0.026295244854506742, "percent_black": 0.08381831085876508}}, "51103": {"past_margin": "R +9", "unemployment": 6.7, "census": {"percent_bachelors": 0.2865206592910364, "median_income": 49456.0, "percent_white": 0.6913756236635781, "population": 11224.0, "percent_hispanic": 0.013987883107626515, "percent_black": 0.28189593727726303}}, "51685": {"past_margin": "D +25", "unemployment": 4.2, "census": {"percent_bachelors": 0.2627491057741441, "median_income": 73460.0, "percent_white": 0.39994663820704374, "population": 14992.0, "percent_hispanic": 0.34044823906083244, "percent_black": 0.1301360725720384}}, "51115": {"past_margin": "R +31", "unemployment": 4.2, "census": {"percent_bachelors": 0.2895387749163393, "median_income": 63157.0, "percent_white": 0.865852291830102, "population": 8923.0, "percent_hispanic": 0.017370839403787964, "percent_black": 0.09951809929395943}}, "51001": {"past_margin": "R +3", "unemployment": 5.4, "census": {"percent_bachelors": 0.18263573709867204, "median_income": 39389.0, "percent_white": 0.6101010101010101, "population": 33165.0, "percent_hispanic": 0.08771295039951757, "percent_black": 0.2862957937584803}}, "51735": {"past_margin": "R +51", "unemployment": 3.8, "census": {"percent_bachelors": 0.357646777472199, "median_income": 83460.0, "percent_white": 0.9296868544988846, "population": 12103.0, "percent_hispanic": 0.02123440469305131, "percent_black": 0.006857803850285053}}, "51133": {"past_margin": "R +15", "unemployment": 6.2, "census": {"percent_bachelors": 0.23614680785442582, "median_income": 50774.0, "percent_white": 0.7015422077922078, "population": 12320.0, "percent_hispanic": 0.004301948051948052, "percent_black": 0.29472402597402597}}, "51800": {"past_margin": "D +15", "unemployment": 5.0, "census": {"percent_bachelors": 0.26110451622047803, "median_income": 66822.0, "percent_white": 0.504264305017724, "population": 85477.0, "percent_hispanic": 0.03315511775097395, "percent_black": 0.41853364062847315}}, "51193": {"past_margin": "D +0", "unemployment": 5.4, "census": {"percent_bachelors": 0.16464363523187053, "median_income": 48750.0, "percent_white": 0.6352894166000685, "population": 17518.0, "percent_hispanic": 0.059824180842561935, "percent_black": 0.2962096129695171}}, "51139": {"past_margin": "R +26", "unemployment": 6.9, "census": {"percent_bachelors": 0.12391964494277038, "median_income": 43063.0, "percent_white": 0.9479606776824931, "population": 23905.0, "percent_hispanic": 0.017276720351390922, "percent_black": 0.016272746287387577}}, "51650": {"past_margin": "D +45", "unemployment": 6.0, "census": {"percent_bachelors": 0.23323690059981905, "median_income": 49879.0, "percent_white": 0.4050283410272892, "population": 136904.0, "percent_hispanic": 0.05002045228773447, "percent_black": 0.502498100858996}}, "51171": {"past_margin": "R +31", "unemployment": 4.3, "census": {"percent_bachelors": 0.19832743860113047, "median_income": 47936.0, "percent_white": 0.8950522975672817, "population": 42545.0, "percent_hispanic": 0.06506052415089905, "percent_black": 0.021647667175931366}}, "51093": {"past_margin": "R +15", "unemployment": 4.6, "census": {"percent_bachelors": 0.2612201127968862, "median_income": 65910.0, "percent_white": 0.7063742327833774, "population": 35518.0, "percent_hispanic": 0.022861647615293655, "percent_black": 0.23379694802635284}}, "51017": {"past_margin": "R +17", "unemployment": 4.1, "census": {"percent_bachelors": 0.19779005524861878, "median_income": 46153.0, "percent_white": 0.8996554694229113, "population": 4644.0, "percent_hispanic": 0.017872523686477175, "percent_black": 0.05921619293712317}}, "51690": {"past_margin": "D +25", "unemployment": 8.8, "census": {"percent_bachelors": 0.16633539073124803, "median_income": 27746.0, "percent_white": 0.47493634048745, "population": 13745.0, "percent_hispanic": 0.043797744634412515, "percent_black": 0.45572935612950166}}, "51149": {"past_margin": "R +10", "unemployment": 5.3, "census": {"percent_bachelors": 0.18549988088620661, "median_income": 61071.0, "percent_white": 0.5695531637312459, "population": 36792.0, "percent_hispanic": 0.06767775603392041, "percent_black": 0.3226244835833877}}, "51175": {"past_margin": "R +3", "unemployment": 4.0, "census": {"percent_bachelors": 0.14766158696794535, "median_income": 49690.0, "percent_white": 0.6002504900893052, "population": 18364.0, "percent_hispanic": 0.012524504465258114, "percent_black": 0.3632106294924853}}, "51710": {"past_margin": "D +44", "unemployment": 5.6, "census": {"percent_bachelors": 0.2559429369567281, "median_income": 44150.0, "percent_white": 0.4408057365829741, "population": 244745.0, "percent_hispanic": 0.07089419599991828, "percent_black": 0.42621095425851396}}, "51680": {"past_margin": "R +11", "unemployment": 5.6, "census": {"percent_bachelors": 0.32274369882439047, "median_income": 39391.0, "percent_white": 0.6289258753510422, "population": 77626.0, "percent_hispanic": 0.03236029165485791, "percent_black": 0.2809239172442223}}, "51141": {"past_margin": "R +39", "unemployment": 5.5, "census": {"percent_bachelors": 0.11232335066266383, "median_income": 34753.0, "percent_white": 0.9007350939286687, "population": 18365.0, "percent_hispanic": 0.025755513204465015, "percent_black": 0.06583174516743806}}, "51071": {"past_margin": "R +26", "unemployment": 5.1, "census": {"percent_bachelors": 0.1699421965317919, "median_income": 45919.0, "percent_white": 0.9550660792951542, "population": 17025.0, "percent_hispanic": 0.013920704845814978, "percent_black": 0.012393538913362702}}, "51043": {"past_margin": "R +14", "unemployment": 4.0, "census": {"percent_bachelors": 0.32202052091554856, "median_income": 75508.0, "percent_white": 0.8769705037483361, "population": 14273.0, "percent_hispanic": 0.03818398374553352, "percent_black": 0.05142576893435157}}, "51590": {"past_margin": "D +22", "unemployment": 7.3, "census": {"percent_bachelors": 0.172156916347731, "median_income": 32173.0, "percent_white": 0.4554842637692019, "population": 42704.0, "percent_hispanic": 0.030793368302735106, "percent_black": 0.48306950168602475}}, "51167": {"past_margin": "R +37", "unemployment": 6.5, "census": {"percent_bachelors": 0.11887941534713764, "median_income": 34768.0, "percent_white": 0.9698003093798341, "population": 28444.0, "percent_hispanic": 0.004429756714948671, "percent_black": 0.01350021094079595}}, "51027": {"past_margin": "R +35", "unemployment": 10.8, "census": {"percent_bachelors": 0.08628607063892511, "median_income": 29678.0, "percent_white": 0.9576911708820673, "population": 23683.0, "percent_hispanic": 0.004475784317865135, "percent_black": 0.023181184816112824}}, "51037": {"past_margin": "R +14", "unemployment": 5.7, "census": {"percent_bachelors": 0.15350622165368066, "median_income": 34820.0, "percent_white": 0.6669086216630373, "population": 12399.0, "percent_hispanic": 0.02395354464069683, "percent_black": 0.30389547544156786}}, "51510": {"past_margin": "D +44", "unemployment": 3.3, "census": {"percent_bachelors": 0.6154756992411059, "median_income": 87319.0, "percent_white": 0.5273797653358102, "population": 146422.0, "percent_hispanic": 0.16467470735272022, "percent_black": 0.21591017743235305}}, "51179": {"past_margin": "R +9", "unemployment": 4.5, "census": {"percent_bachelors": 0.3707175139221789, "median_income": 98721.0, "percent_white": 0.6636568848758465, "population": 134672.0, "percent_hispanic": 0.10131281929428537, "percent_black": 0.17204021622906024}}, "51035": {"past_margin": "R +39", "unemployment": 5.3, "census": {"percent_bachelors": 0.12962540493680705, "median_income": 33495.0, "percent_white": 0.9545865265553362, "population": 29881.0, "percent_hispanic": 0.02847963588902647, "percent_black": 0.008266122285064088}}, "51007": {"past_margin": "R +27", "unemployment": 4.4, "census": {"percent_bachelors": 0.15639445300462249, "median_income": 55870.0, "percent_white": 0.7210122218740207, "population": 12764.0, "percent_hispanic": 0.009009714822939517, "percent_black": 0.24945158257599498}}, "51187": {"past_margin": "R +21", "unemployment": 4.7, "census": {"percent_bachelors": 0.19659430850655826, "median_income": 60560.0, "percent_white": 0.8831471868281684, "population": 38142.0, "percent_hispanic": 0.037675003932672646, "percent_black": 0.03791096429133239}}, "51740": {"past_margin": "D +40", "unemployment": 6.2, "census": {"percent_bachelors": 0.19470804074144366, "median_income": 46239.0, "percent_white": 0.39762725634589147, "population": 96007.0, "percent_hispanic": 0.03473705042340663, "percent_black": 0.5284614663514119}}, "51600": {"past_margin": "D +16", "unemployment": 3.4, "census": {"percent_bachelors": 0.5351871133704906, "median_income": 100584.0, "percent_white": 0.601693112689837, "population": 23507.0, "percent_hispanic": 0.16263240736801804, "percent_black": 0.04709235546858383}}, "51199": {"past_margin": "R +21", "unemployment": 4.3, "census": {"percent_bachelors": 0.42019791930981987, "median_income": 80900.0, "percent_white": 0.7335126428397764, "population": 65808.0, "percent_hispanic": 0.051163992219790906, "percent_black": 0.13451252127400923}}, "51049": {"past_margin": "R +2", "unemployment": 5.3, "census": {"percent_bachelors": 0.16395365889426602, "median_income": 41484.0, "percent_white": 0.6307987091569182, "population": 9916.0, "percent_hispanic": 0.001008471157724889, "percent_black": 0.3443929003630496}}, "51099": {"past_margin": "R +19", "unemployment": 4.7, "census": {"percent_bachelors": 0.31777819761949744, "median_income": 83071.0, "percent_white": 0.7426455629246856, "population": 24577.0, "percent_hispanic": 0.03950848354152256, "percent_black": 0.18383041054644586}}, "51159": {"past_margin": "R +16", "unemployment": 4.6, "census": {"percent_bachelors": 0.1288765359859567, "median_income": 47199.0, "percent_white": 0.6161816578483245, "population": 9072.0, "percent_hispanic": 0.05952380952380952, "percent_black": 0.2744708994708995}}, "51077": {"past_margin": "R +38", "unemployment": 5.8, "census": {"percent_bachelors": 0.10829755541925874, "median_income": 28892.0, "percent_white": 0.9383153064568994, "population": 15255.0, "percent_hispanic": 0.02844968862667978, "percent_black": 0.019206817436905933}}, "51520": {"past_margin": "R +31", "unemployment": 5.3, "census": {"percent_bachelors": 0.20377965420184962, "median_income": 33616.0, "percent_white": 0.8911622620062518, "population": 17595.0, "percent_hispanic": 0.006990622335890878, "percent_black": 0.06643932935493038}}, "51550": {"past_margin": "D +1", "unemployment": 4.5, "census": {"percent_bachelors": 0.2936258654334518, "median_income": 70176.0, "percent_white": 0.5954428315977701, "population": 228168.0, "percent_hispanic": 0.04860015427229059, "percent_black": 0.2979427439430595}}, "51700": {"past_margin": "D +30", "unemployment": 5.4, "census": {"percent_bachelors": 0.24085643287134256, "median_income": 51000.0, "percent_white": 0.45495197450403063, "population": 181362.0, "percent_hispanic": 0.08020423241913963, "percent_black": 0.4010321897641182}}, "51019": {"past_margin": "R +45", "unemployment": 4.4, "census": {"percent_bachelors": 0.2632152487902183, "median_income": 56043.0, "percent_white": 0.8860952028251352, "population": 75607.0, "percent_hispanic": 0.01834486224820453, "percent_black": 0.06953059901860939}}, "51101": {"past_margin": "R +24", "unemployment": 4.2, "census": {"percent_bachelors": 0.19074257872417216, "median_income": 63560.0, "percent_white": 0.7608600810221253, "population": 16045.0, "percent_hispanic": 0.008039887815518853, "percent_black": 0.19046431910252415}}, "51840": {"past_margin": "D +1", "unemployment": 4.3, "census": {"percent_bachelors": 0.28065333708814416, "median_income": 44731.0, "percent_white": 0.6823646923902187, "population": 27031.0, "percent_hispanic": 0.1604824090858644, "percent_black": 0.10783914764529615}}, "51147": {"past_margin": "D +13", "unemployment": 6.5, "census": {"percent_bachelors": 0.22430700332020692, "median_income": 37238.0, "percent_white": 0.621305099394987, "population": 23140.0, "percent_hispanic": 0.023509075194468453, "percent_black": 0.3356957649092481}}, "51031": {"past_margin": "R +39", "unemployment": 4.8, "census": {"percent_bachelors": 0.18858560794044665, "median_income": 47055.0, "percent_white": 0.80810825597724, "population": 54833.0, "percent_hispanic": 0.018948443455583316, "percent_black": 0.13754490908759323}}, "51051": {"past_margin": "R +26", "unemployment": 10.1, "census": {"percent_bachelors": 0.10194261272500446, "median_income": 33106.0, "percent_white": 0.9814885985139636, "population": 15612.0, "percent_hispanic": 0.007302075326671791, "percent_black": 0.007558288496028696}}, "51095": {"past_margin": "R +12", "unemployment": 4.3, "census": {"percent_bachelors": 0.4609060067850728, "median_income": 76705.0, "percent_white": 0.7683010654141368, "population": 69832.0, "percent_hispanic": 0.05100813380685073, "percent_black": 0.13720071027609118}}, "51630": {"past_margin": "D +27", "unemployment": 5.3, "census": {"percent_bachelors": 0.3770830642035913, "median_income": 49454.0, "percent_white": 0.6015319915890658, "population": 26632.0, "percent_hispanic": 0.10802793631721237, "percent_black": 0.2243166115950736}}, "51135": {"past_margin": "R +1", "unemployment": 4.5, "census": {"percent_bachelors": 0.12229379137591698, "median_income": 35911.0, "percent_white": 0.5527418126428028, "population": 15756.0, "percent_hispanic": 0.039223153084539226, "percent_black": 0.3935643564356436}}, "51111": {"past_margin": "R +5", "unemployment": 5.2, "census": {"percent_bachelors": 0.12460687561002061, "median_income": 37881.0, "percent_white": 0.5995894844872504, "population": 12667.0, "percent_hispanic": 0.038998973711218125, "percent_black": 0.34467514012789136}}, "51191": {"past_margin": "R +43", "unemployment": 4.8, "census": {"percent_bachelors": 0.23508205813396527, "median_income": 42458.0, "percent_white": 0.9579085587146426, "population": 54833.0, "percent_hispanic": 0.01396968978534824, "percent_black": 0.014480331187423631}}, "51113": {"past_margin": "R +19", "unemployment": 3.5, "census": {"percent_bachelors": 0.23109018936557185, "median_income": 51641.0, "percent_white": 0.8541792852816474, "population": 13208.0, "percent_hispanic": 0.01067534827377347, "percent_black": 0.09577528770442156}}, "51131": {"past_margin": "D +16", "unemployment": 6.1, "census": {"percent_bachelors": 0.20396039603960395, "median_income": 34656.0, "percent_white": 0.5417006691692509, "population": 12254.0, "percent_hispanic": 0.07801534192916598, "percent_black": 0.3687775420270932}}, "51029": {"past_margin": "D +2", "unemployment": 5.8, "census": {"percent_bachelors": 0.11162264760520152, "median_income": 38484.0, "percent_white": 0.6112347703842549, "population": 17072.0, "percent_hispanic": 0.01956419868791003, "percent_black": 0.3465909090909091}}, "51053": {"past_margin": "R +3", "unemployment": 5.3, "census": {"percent_bachelors": 0.1372799836266885, "median_income": 52328.0, "percent_white": 0.6281213160432966, "population": 27993.0, "percent_hispanic": 0.02693530525488515, "percent_black": 0.3274390026077948}}, "51069": {"past_margin": "R +28", "unemployment": 4.0, "census": {"percent_bachelors": 0.2820578542658367, "median_income": 68719.0, "percent_white": 0.8555308110529132, "population": 80377.0, "percent_hispanic": 0.06959702402428555, "percent_black": 0.04497555270786419}}}